{"nodes": [{"id": "completeprofile", "label": "CompleteProfile.ts", "file_type": "code", "source_file": "src/types/CompleteProfile.ts", "source_location": "L1"}], "edges": [{"source": "completeprofile", "target": "userprofile", "relation": "imports_from", "confidence": "EXTRACTED", "source_file": "src/types/CompleteProfile.ts", "source_location": "L1", "weight": 1.0}, {"source": "completeprofile", "target": "volunteerprofile", "relation": "imports_from", "confidence": "EXTRACTED", "source_file": "src/types/CompleteProfile.ts", "source_location": "L2", "weight": 1.0}]}